portip/__init__.py
portip/portip.py
portip-1.1.0.dist-info/LICENSE
portip-1.1.0.dist-info/METADATA
portip-1.1.0.dist-info/WHEEL
portip-1.1.0.dist-info/entry_points.txt
portip-1.1.0.dist-info/top_level.txt
portip-1.1.0.dist-info/RECORD
