Metadata-Version: 2.1
Name: portip
Version: 1.1.0
Summary: A simple IP and port scanner tool.
Author: Pabitra Banerjee
Author-email: <rockstarpabitra2204@gmail.com>
Keywords: python,port scanner,networking,IP,port
Classifier: Development Status :: 3 - Alpha
Classifier: Intended Audience :: Developers
Classifier: Programming Language :: Python :: 3
Classifier: License :: OSI Approved :: MIT License
Classifier: Operating System :: Unix
Classifier: Operating System :: MacOS :: MacOS X
Classifier: Operating System :: Microsoft :: Windows
Requires-Python: >=3.6
License-File: LICENSE
